transpdf
