Metadata-Version: 2.4
Name: transpdf
Version: 0.1.2
Summary: Translate PDFs to any language by also preserving layout and quality.
Author: Mukesh Anand G
Author-email: ai.mukeshanandg@gmail.com
License: MIT
Classifier: Development Status :: 4 - Beta
Classifier: Intended Audience :: End Users/Desktop
Classifier: License :: OSI Approved :: MIT License
Classifier: Programming Language :: Python :: 3
Classifier: Programming Language :: JavaScript
Classifier: Operating System :: Microsoft :: Windows
Classifier: Topic :: Utilities
Classifier: Topic :: Text Processing :: Linguistic
Requires-Python: >=3.8
Requires-Dist: click>=8.0
Dynamic: author
Dynamic: author-email
Dynamic: classifier
Dynamic: description
Dynamic: description-content-type
Dynamic: license
Dynamic: requires-dist
Dynamic: requires-python
Dynamic: summary
